<?xml version="1.0" encoding="UTF-8"?>
<objects serializationModel="Studio.02.01.00">
	<object class="EncodingSetting" id="{692ba6dc-faf4-4997-b7de-3fb8d07e04ac}">
		<property name="encodingFormat">
			<value>3</value>
		</property>
		<property name="quality">
			<value>37</value>
		</property>
		<relationship name="platform">
			<destination>{ea37c4c4-dfa3-467c-8e43-a5e5640eea86}</destination>
		</relationship>
		<relationship name="encodable">
			<destination>{ea37c4c4-dfa3-467c-8e43-a5e5640eea86}</destination>
		</relationship>
	</object>
</objects>
